pytest_check_links/__init__.py
pytest_check_links/__main__.py
pytest_check_links/_version.py
pytest_check_links/args.py
pytest_check_links/plugin.py
pytest_check_links/py.typed
pytest_check_links-0.10.1.dist-info/METADATA
pytest_check_links-0.10.1.dist-info/WHEEL
pytest_check_links-0.10.1.dist-info/entry_points.txt
pytest_check_links-0.10.1.dist-info/licenses/LICENSE
pytest_check_links-0.10.1.dist-info/RECORD
