Metadata-Version: 2.3
Name: pytest_check_links
Version: 0.10.1
Summary: Check links in files
Project-URL: Homepage, https://github.com/jupyterlab/pytest-check-links
Author-email: Jupyter Development Team <jupyter@googlegroups.com>
License: Copyright (c) 2019 Project Jupyter Contributors
License-File: LICENSE
Keywords: documentation,html,links,testing
Classifier: Framework :: Jupyter
Classifier: Framework :: Pytest
Classifier: Intended Audience :: Developers
Classifier: License :: OSI Approved :: BSD License
Classifier: Operating System :: OS Independent
Classifier: Programming Language :: Python
Classifier: Programming Language :: Python :: 3 :: Only
Classifier: Topic :: Documentation
Classifier: Topic :: Documentation :: Sphinx
Classifier: Topic :: Software Development :: Quality Assurance
Classifier: Topic :: Software Development :: Testing
Classifier: Typing :: Typed
Requires-Python: >=3.8
Requires-Dist: docutils>=0.20.1
Requires-Dist: html5lib>=1.1
Requires-Dist: nbconvert>=7.1
Requires-Dist: nbformat>=5.1
Requires-Dist: pytest<9,>=7.0
Requires-Dist: requests>=2.22
Provides-Extra: cache
Requires-Dist: requests-cache>=0.9.7; extra == 'cache'
Provides-Extra: test
Requires-Dist: flaky; extra == 'test'
Requires-Dist: pre-commit; extra == 'test'
Requires-Dist: requests-cache>=0.9.7; extra == 'test'
